dspy_cli/__init__.py
dspy_cli/cli.py
dspy_cli/commands/__init__.py
dspy_cli/commands/generate.py
dspy_cli/commands/new.py
dspy_cli/commands/serve.py
dspy_cli/config/__init__.py
dspy_cli/config/loader.py
dspy_cli/config/validator.py
dspy_cli/discovery/__init__.py
dspy_cli/discovery/gateway_finder.py
dspy_cli/discovery/module_finder.py
dspy_cli/gateway/__init__.py
dspy_cli/gateway/api.py
dspy_cli/gateway/base.py
dspy_cli/gateway/cron.py
dspy_cli/gateway/types.py
dspy_cli/server/__init__.py
dspy_cli/server/app.py
dspy_cli/server/auth.py
dspy_cli/server/execution.py
dspy_cli/server/logging.py
dspy_cli/server/mcp.py
dspy_cli/server/metrics.py
dspy_cli/server/routes.py
dspy_cli/server/runner.py
dspy_cli/server/scheduler.py
dspy_cli/server/ui.py
dspy_cli/templates/.dockerignore.template
dspy_cli/templates/Dockerfile.template
dspy_cli/templates/README.md.template
dspy_cli/templates/__init__.py
dspy_cli/templates/dspy.config.yaml.template
dspy_cli/templates/env.template
dspy_cli/templates/gitignore.template
dspy_cli/templates/pyproject.toml.template
dspy_cli/templates/code_templates/__init__.py
dspy_cli/templates/code_templates/gateway_api.py.template
dspy_cli/templates/code_templates/gateway_cron.py.template
dspy_cli/templates/code_templates/module_chain_of_thought.py.template
dspy_cli/templates/code_templates/module_multi_chain_comparison.py.template
dspy_cli/templates/code_templates/module_predict.py.template
dspy_cli/templates/code_templates/module_program_of_thought.py.template
dspy_cli/templates/code_templates/module_react.py.template
dspy_cli/templates/code_templates/module_refine.py.template
dspy_cli/templates/code_templates/signature.py.template
dspy_cli/templates/code_templates/test_modules.py.template
dspy_cli/templates/ui/templates.py
dspy_cli/templates/ui/static/script.js
dspy_cli/templates/ui/static/style.css
dspy_cli/utils/__init__.py
dspy_cli/utils/constants.py
dspy_cli/utils/interactive.py
dspy_cli/utils/model_utils.py
dspy_cli/utils/openapi.py
dspy_cli-0.1.12.dist-info/licenses/LICENSE
dspy_cli-0.1.12.dist-info/METADATA
dspy_cli-0.1.12.dist-info/WHEEL
dspy_cli-0.1.12.dist-info/entry_points.txt
dspy_cli-0.1.12.dist-info/top_level.txt
dspy_cli-0.1.12.dist-info/RECORD
